Metadata-Version: 2.1
Name: fopcalculator
Version: 0.1
Summary: Calculate Four Operations and Find Root of n
Author: Fuad Yagci
